klara/__init__.py
klara/cli.py
klara/common/__init__.py
klara/common/cfg_common.py
klara/common/common.py
klara/contract/__init__.py
klara/contract/__main__.py
klara/contract/config.py
klara/contract/solver.py
klara/core/__init__.py
klara/core/_ast.py
klara/core/base_manager.py
klara/core/bases.py
klara/core/cfg.py
klara/core/config.py
klara/core/context_mod.py
klara/core/decorators.py
klara/core/exceptions.py
klara/core/html/__init__.py
klara/core/html/infer_server.py
klara/core/html/report.py
klara/core/inference.py
klara/core/manager.py
klara/core/node_classes.py
klara/core/nodes.py
klara/core/protocols.py
klara/core/raw_building.py
klara/core/recipe.py
klara/core/scoped_node_classes.py
klara/core/source_utils.py
klara/core/ssa.py
klara/core/ssa_visitors.py
klara/core/transform.py
klara/core/tree/__init__.py
klara/core/tree/infer_proxy.py
klara/core/tree_rewriter.py
klara/core/typeshed/stdlib/2and3/builtins.pyi
klara/core/typeshed/stdlib/2and3/math.pyi
klara/core/use_def_chain.py
klara/core/utilities.py
klara/examples/cover_select_field/__init__.py
klara/examples/cover_select_field/cover_select_field.py
klara/examples/cover_select_field/source.py
klara/examples/custom_test_gen.py
klara/examples/extending_inference.py
klara/examples/extending_transform.py
klara/examples/infer_z3.py
klara/examples/simple_inference.py
klara/html/htmlfiles/bootstrap/css/bootstrap-grid.css
klara/html/htmlfiles/bootstrap/css/bootstrap-grid.css.map
klara/html/htmlfiles/bootstrap/css/bootstrap-grid.min.css
klara/html/htmlfiles/bootstrap/css/bootstrap-grid.min.css.map
klara/html/htmlfiles/bootstrap/css/bootstrap-reboot.css
klara/html/htmlfiles/bootstrap/css/bootstrap-reboot.css.map
klara/html/htmlfiles/bootstrap/css/bootstrap-reboot.min.css
klara/html/htmlfiles/bootstrap/css/bootstrap-reboot.min.css.map
klara/html/htmlfiles/bootstrap/css/bootstrap.css
klara/html/htmlfiles/bootstrap/css/bootstrap.css.map
klara/html/htmlfiles/bootstrap/css/bootstrap.min.css
klara-0.6.2.dist-info/entry_points.txt
klara-0.6.2.dist-info/LICENSE.rst
klara-0.6.2.dist-info/WHEEL
klara-0.6.2.dist-info/METADATA
klara-0.6.2.dist-info/RECORD
