Metadata-Version: 2.1
Name: klara
Version: 0.6.2
Summary: Automatic test case generation and static analysis library
Home-page: https://github.com/usagitoneko97/klara
License: LGPL-3.0-or-later
Keywords: unit test,test generation,static analysis
Author: Ho Guo Xian
Author-email: hogouxian@gmail.com
Requires-Python: >=3.6.2,<4.0
Classifier: Development Status :: 3 - Alpha
Classifier: Environment :: Console
Classifier: Intended Audience :: Developers
Classifier: Intended Audience :: Education
Classifier: Intended Audience :: Science/Research
Classifier: License :: OSI Approved :: GNU Lesser General Public License v3 or later (LGPLv3+)
Classifier: Operating System :: MacOS :: MacOS X
Classifier: Operating System :: Microsoft :: Windows
Classifier: Operating System :: POSIX :: Linux
Classifier: Programming Language :: Python :: 3
Classifier: Programming Language :: Python :: 3.7
Classifier: Programming Language :: Python :: 3.8
Classifier: Programming Language :: Python :: 3.9
Classifier: Topic :: Education :: Testing
Classifier: Topic :: Software Development :: Testing
Classifier: Topic :: Software Development :: Testing :: Unit
Classifier: Typing :: Typed
Requires-Dist: ConfigArgParse (>=1.5.2,<2.0.0)
Requires-Dist: astor (>=0.8.1,<0.9.0)
Requires-Dist: typed-ast (>=1.4.3,<2.0.0)
Requires-Dist: z3-solver (>=4.8.12,<5.0.0)
Project-URL: Documentation, https://klara-py.readthedocs.io
Project-URL: Repository, https://github.com/usagitoneko97/klara
